jynxzzz/__init__.py
jynxzzz/plot_utils.py
jynxzzz-0.4.dist-info/METADATA
jynxzzz-0.4.dist-info/WHEEL
jynxzzz-0.4.dist-info/top_level.txt
jynxzzz-0.4.dist-info/RECORD
